mq/__init__.py
mq/base.py
mq/config.py
mq/constants.py
mq/enum.py
mq/jobstore.py
mq/mongoqueue.py
mq/utils.py
mq/dashboard/__init__.py
mq/dashboard/example.py
mq/dashboard/router.py
mq/dashboard/templates/dashboard/base.html
mq/dashboard/templates/dashboard/error.html
mq/dashboard/templates/dashboard/index.html
mq/dashboard/templates/dashboard/job_detail.html
mq/dashboard/templates/dashboard/store_detail.html
mq/lib/heartbeat.py
mq/lib/scheduler.py
mq/models/async_worker.py
mq/models/base.py
mq/models/job.py
mq/models/retry.py
mq/models/worker.py
mq_python-0.1.0.dist-info/METADATA
mq_python-0.1.0.dist-info/WHEEL
mq_python-0.1.0.dist-info/licenses/LICENSE
mq_python-0.1.0.dist-info/RECORD
