Metadata-Version: 2.4
Name: mq-python
Version: 0.1.0
Summary: An extensible and scalable MongoDB-based job queue system for Python
Project-URL: Homepage, https://github.com/viperadnan-git/mq-python#readme
Project-URL: Bug Tracker, https://github.com/viperadnan-git/mq-python/issues
Project-URL: Source Code, https://github.com/viperadnan-git/mq-python
Project-URL: Documentation, https://github.com/viperadnan-git/mq-python#readme
Author-email: Adnan Ahmad <viperadnan@gmail.com>
Maintainer-email: Adnan Ahmad <viperadnan@gmail.com>
License-File: LICENSE
Keywords: background,job,jobs,mongodb,queue,scheduler,task,threading,worker
Classifier: Development Status :: 4 - Beta
Classifier: Intended Audience :: Developers
Classifier: Programming Language :: Python :: 3
Classifier: Programming Language :: Python :: 3.11
Classifier: Programming Language :: Python :: 3.12
Classifier: Topic :: Software Development :: Libraries :: Python Modules
Classifier: Topic :: Utilities
Requires-Python: >=3.11
Requires-Dist: apscheduler>=3.11.0
Requires-Dist: pydantic-extra-types>=2.10.4
Requires-Dist: pydantic-settings>=2.9.1
Requires-Dist: pydantic>=2.11.4
Requires-Dist: pymongo>=4.12.1
Provides-Extra: fastapi
Requires-Dist: fastapi>=0.115.12; extra == 'fastapi'
Requires-Dist: jinja2>=3.1.6; extra == 'fastapi'
Requires-Dist: python-multipart>=0.0.20; extra == 'fastapi'
Requires-Dist: uvicorn>=0.34.2; extra == 'fastapi'
